README.md
debhelper.py
setup.py
debhelper.egg-info/PKG-INFO
debhelper.egg-info/SOURCES.txt
debhelper.egg-info/dependency_links.txt
debhelper.egg-info/requires.txt
debhelper.egg-info/top_level.txt